tutortranslations/__about__.py
tutortranslations/__init__.py
tutortranslations/plugin.py
tutortranslations/templates/mfe/i18n/account/ar.json
tutortranslations/templates/mfe/i18n/account/es.json
tutortranslations/templates/mfe/i18n/account/fr.json
tutortranslations/templates/mfe/i18n/account/pl.json
tutortranslations/templates/mfe/i18n/learning/ar.json
tutortranslations/templates/mfe/i18n/learning/es.json
tutortranslations/templates/mfe/i18n/learning/fr.json
tutortranslations/templates/mfe/i18n/learning/pl.json
tutortranslations/templates/mfe/i18n/profile/ar.json
tutortranslations/templates/mfe/i18n/profile/es.json
tutortranslations/templates/mfe/i18n/profile/fr.json
tutortranslations/templates/mfe/i18n/profile/pl.json
tutortranslations/templates/openedx/locale/.gitignore
tutortranslations/templates/openedx/locale/ar/LC_MESSAGES/django.po
tutortranslations/templates/openedx/locale/es/LC_MESSAGES/django.po
tutortranslations/templates/openedx/locale/fr/LC_MESSAGES/django.po
tutortranslations/templates/openedx/locale/pl/LC_MESSAGES/django.po
tutor_contrib_translations-17.0.0.dist-info/METADATA
tutor_contrib_translations-17.0.0.dist-info/WHEEL
tutor_contrib_translations-17.0.0.dist-info/entry_points.txt
tutor_contrib_translations-17.0.0.dist-info/top_level.txt
tutor_contrib_translations-17.0.0.dist-info/RECORD
