Metadata-Version: 2.1
Name: tutor-contrib-translations
Version: 17.0.0
Summary: Translations plugin for Tutor
Home-page: https://github.com/aulasneo/tutor-contrib-translations
Author: Andrés González
License: AGPLv3
Project-URL: Code, https://github.com/aulasneo/tutor-contrib-translations
Project-URL: Issue tracker, https://github.com/aulasneo/tutor-contrib-translations/issues
Classifier: Development Status :: 3 - Alpha
Classifier: Intended Audience :: Developers
Classifier: License :: OSI Approved :: GNU Affero General Public License v3
Classifier: Operating System :: OS Independent
Classifier: Programming Language :: Python
Classifier: Programming Language :: Python :: 3.7
Classifier: Programming Language :: Python :: 3.8
Classifier: Programming Language :: Python :: 3.9
Classifier: Programming Language :: Python :: 3.10
Requires-Python: >=3.7
Requires-Dist: tutor <18.0.0,>=17.0.0
